mosaicprot/__init__.py
mosaicprot/cli.py
mosaicprot/utils.py
mosaicprot-0.1.8.dist-info/licenses/LICENSE
mosaicprot-0.1.8.dist-info/METADATA
mosaicprot-0.1.8.dist-info/WHEEL
mosaicprot-0.1.8.dist-info/entry_points.txt
mosaicprot-0.1.8.dist-info/top_level.txt
mosaicprot-0.1.8.dist-info/RECORD
