Metadata-Version: 2.4
Name: mosaicprot
Version: 0.1.8
Summary: MosaicProt CLI: Detect ORFs, Find Alternative ORFs, Generate Mosaic Proteins
Home-page: https://github.com/umutcakir/MosaicProt
Author: Umut Cakir & Ali Yurtseven
Author-email: hpumut@gmail.com
Classifier: Programming Language :: Python :: 3
Classifier: License :: OSI Approved :: MIT License
Classifier: Operating System :: OS Independent
Requires-Python: >=3.6
License-File: LICENSE
Requires-Dist: biopython==1.85
Requires-Dist: pandas==2.2.3
Dynamic: author
Dynamic: author-email
Dynamic: classifier
Dynamic: description
Dynamic: description-content-type
Dynamic: home-page
Dynamic: license-file
Dynamic: requires-dist
Dynamic: requires-python
Dynamic: summary
